{"sequenceId":"845362181743","id":"34207110663","language":"English","title":"Port de Roche ce soir","content":"  Le RHEU ce WEEK-END  ","contentWithMarkup":"Le RHEU ce WEEK-END","tags":[],"publishedDate":"2018-06-02T05:30:00Z","harvestDate":"2018-06-02T21:24:22Z","estimatedPublishedDate":"2018-06-02T05:30:00Z","url":"http://ct.moreover.com/?a=34207110663&p=1u0&v=1&x=tMbrUCmS5rXR4Dc3Erpkiw","originalUrl":"http://guipry-ma-ville.over-blog.com/2018/05/port-de-roche-ce-soir.html","outboundUrls":[],"wordCount":"4","dataFormat":"text","duplicateGroupId":"34207110663","media":{"audio":[],"images":[],"video":[],"logo":[]},"publishingPlatform":{},"adultLanguage":"false","topics":[{"name":"European business news","group":"Business"}],"companies":[],"author":{"name":"Guipry","publishingPlatform":{}},"licenses":[],"source":{"name":"Le blog de Guipry-Messac","homeUrl":"http://guipry-ma-ville.over-blog.com/","location":{},"feed":{"id":"50326329","name":"Le blog de Guipry-Messac","mediaType":"Blog","publishingPlatform":"OverBlog","generator":"Overblog - https://www.over-blog.com","description":"Découvrir la Ville De Guipry-Messac\nDépartement : 35 Ille-et-Vilaine FR\nPopulation :  7200  habitants en 2018 \nSuperficie : 51 km²\nDensité : 59 hab/km²\nAltitude : 40 m\nLongitude : -1.841667 E\nLatitude : 47.825279 N","tags":[],"copyright":"Copyright 2015 guipry-ma-ville.over-blog.com","language":"Unassigned","dataFormat":"text","rank":{"autoRank":"10","autoRankOrder":"194399","inboundLinkCount":"0"},"inWhiteList":"true","autoTopics":[]}},"es_id":86990320}