{"sequenceId":"845362000090","id":"34207104221","language":"English","title":"UMC hosts Ramadan dinner for scores of Muslims","content":"Hundreds of congregants at the United Methodist Church’s (UMC) largest megachurch in the United States celebrated Islam last week by hosting a Ramadan dinner to “demonstrate the love of Christ” to the Muslim community.  via OneNewsNow.com Front Page Stories https://ift.tt/2kGHgGB","contentWithMarkup":"<p><img width=\"350\" height=\"219\" src=\"/media/5613636/muslim_man_praying_350x219.jpg\" alt=\"Muslim man praying\" class=\"ImageFloatLeft\" />Hundreds of congregants at the United Methodist Church’s (UMC) largest megachurch in the United States celebrated Islam last week by hosting a Ramadan dinner to “demonstrate the love of Christ” to the Muslim community.</p><br /><br />via OneNewsNow.com Front Page Stories https://ift.tt/2kGHgGB","tags":["Breaking News","IFTTT","OneNewsNow.com Front Page Stories"],"publishedDate":"2018-06-02T15:17:06Z","harvestDate":"2018-06-02T21:22:35Z","estimatedPublishedDate":"2018-06-02T15:17:06Z","url":"http://ct.moreover.com/?a=34207104221&p=1u0&v=1&x=o13SVFYGoyL5wP5QYiKLDg","originalUrl":"http://theirontimes.blogspot.com/2018/06/umc-hosts-ramadan-dinner-for-scores-of.html","commentsUrl":"http://theirontimes.blogspot.com/2018/06/umc-hosts-ramadan-dinner-for-scores-of.html#comment-form","outboundUrls":["https://ift.tt/2kGHgGB"],"wordCount":"40","dataFormat":"text","duplicateGroupId":"34206609176","media":{"audio":[],"images":[],"video":[],"logo":[]},"publishingPlatform":{},"adultLanguage":"false","topics":[{"name":"Religion news","group":"Society"}],"companies":[],"author":{"name":"Vince Wylde","publishingPlatform":{}},"licenses":[],"source":{"name":"The Iron Times","homeUrl":"http://theirontimes.blogspot.com/","location":{},"feed":{"id":"372465404","name":"The Iron Times","mediaType":"Blog","publishingPlatform":"Blogger","generator":"Blogger http://www.blogger.com","tags":["IFTTT","TheBlaze","Breaking News","OneNewsNow.com Front Page Stories","TheBlaze.com - Blog","Poor Richard's News","Poor Richards News","Poor Richard's News  RSS Feed","TheBlaze.com","Obamacare","Affordable Healthcare","Liberalism","Obama","Terrorism","Democrats","Extremism","Extremist I"],"language":"English","dataFormat":"text","rank":{"autoRank":"10","autoRankOrder":"194399","inboundLinkCount":"0"},"inWhiteList":"true","autoTopics":[]}},"es_id":86990065}