{"sequenceId":"845362200377","id":"34207111279","language":"English","title":"Aigoin Testing @ Hudy Arena Indoor","content":"By XRAY","contentWithMarkup":"<p><img title=\"aigoinhudyarena020618\" style=\"border-top: 0px; border-right: 0px; background-image: none; border-bottom: 0px; padding-top: 0px; padding-left: 0px; margin: 5px 8px 8px 0px; border-left: 0px; display: inline; padding-right: 0px\" border=\"0\" alt=\"aigoinhudyarena020618\" src=\"http://www.rcspecial.com/news/wp-content/uploads/2018/06/aigoinhudyarena020618.jpg\" width=\"504\" height=\"386\" /></p>\n<p>By XRAY</p>","tags":["Buggy","Gas","aigoin","hudy arena","xray"],"publishedDate":"2018-06-02T13:37:46Z","harvestDate":"2018-06-02T21:24:29Z","estimatedPublishedDate":"2018-06-02T13:37:46Z","url":"http://ct.moreover.com/?a=34207111279&p=1u0&v=1&x=Olx4c3hyQx9HbLyXtZzGvg","originalUrl":"http://www.rcspecial.com/news/aigoin-testing-hudy-arena-indoor/","outboundUrls":[],"wordCount":"2","dataFormat":"text","duplicateGroupId":"34207111279","media":{"audio":[],"images":[{"url":"http://www.rcspecial.com/news/wp-content/uploads/2018/06/aigoinhudyarena020618.jpg"}],"video":[],"logo":[]},"publishingPlatform":{},"adultLanguage":"false","topics":[],"companies":[],"author":{"name":"Admin","publishingPlatform":{}},"licenses":[],"source":{"name":"RCSpecial.com","homeUrl":"http://www.rcspecial.com/news","location":{"country":"United States","countryCode":"US","region":"Americas","subregion":"Northern America"},"feed":{"id":"68076775","name":"RCSpecial.com","mediaType":"Blog","publishingPlatform":"WordPress","generator":"https://wordpress.org/?v=4.9.6","description":"Radio Control News","tags":[],"language":"English","dataFormat":"text","rank":{"autoRank":"10","autoRankOrder":"194399","inboundLinkCount":"0"},"inWhiteList":"true","autoTopics":[]}},"es_id":86990354}