{"sequenceId":"845363894720","id":"34207167409","language":"English","title":"West Coast Synthesis in Audulus","content":"Started streaming 10 minutes ago audulus \"Download the patch here: https://forum.audulus.com/t/west-coas... http://www.audulus.com http://forum.audulus.com\"","contentWithMarkup":"Started streaming 10 minutes ago audulus\n\n\"Download the patch here: https://forum.audulus.com/t/west-coas...\n\nhttp://www.audulus.com\nhttp://forum.audulus.com\"<div class=\"feedflare\">\n<a href=\"http://feeds.feedburner.com/~ff/Matrixsynth?a=WIKK2-Kwx-s:oDOSD79Afkk:yIl2AUoC8zA\"><img src=\"http://feeds.feedburner.com/~ff/Matrixsynth?d=yIl2AUoC8zA\" border=\"0\"></img></a> <a href=\"http://feeds.feedburner.com/~ff/Matrixsynth?a=WIKK2-Kwx-s:oDOSD79Afkk:7Q72WNTAKBA\"><img src=\"http://feeds.feedburner.com/~ff/Matrixsynth?d=7Q72WNTAKBA\" border=\"0\"></img></a> <a href=\"http://feeds.feedburner.com/~ff/Matrixsynth?a=WIKK2-Kwx-s:oDOSD79Afkk:V_sGLiPBpWU\"><img src=\"http://feeds.feedburner.com/~ff/Matrixsynth?i=WIKK2-Kwx-s:oDOSD79Afkk:V_sGLiPBpWU\" border=\"0\"></img></a> <a href=\"http://feeds.feedburner.com/~ff/Matrixsynth?a=WIKK2-Kwx-s:oDOSD79Afkk:qj6IDK7rITs\"><img src=\"http://feeds.feedburner.com/~ff/Matrixsynth?d=qj6IDK7rITs\" border=\"0\"></img></a>\n</div><img src=\"http://feeds.feedburner.com/~r/Matrixsynth/~4/WIKK2-Kwx-s\" height=\"1\" width=\"1\" alt=\"\"/>","tags":["Audulus","iOS","Soft Synths","synth tutorials"],"publishedDate":"2018-06-02T18:11:11Z","harvestDate":"2018-06-02T21:38:27Z","estimatedPublishedDate":"2018-06-02T18:11:11Z","url":"http://ct.moreover.com/?a=34207167409&p=1u0&v=1&x=-a1b6J3aGZf-gYcmZnTtIA","originalUrl":"https://www.matrixsynth.com/2018/06/west-coast-synthesis-in-audulus.html","commentsUrl":"http://www.matrixsynth.com/2018/06/west-coast-synthesis-in-audulus.html#comment-form","outboundUrls":["https://forum.audulus.com/t/west-coast-synthesis-tutorial-livestream-june-2nd-2pm-est/662/5","http://www.audulus.com/","http://forum.audulus.com/","http://www.audulus.com","http://forum.audulus.com%22","http://feeds.feedburner.com/~ff/Matrixsynth?a=WIKK2-Kwx-s:oDOSD79Afkk:yIl2AUoC8zA","http://feeds.feedburner.com/~ff/Matrixsynth?a=WIKK2-Kwx-s:oDOSD79Afkk:7Q72WNTAKBA","http://feeds.feedburner.com/~ff/Matrixsynth?a=WIKK2-Kwx-s:oDOSD79Afkk:V_sGLiPBpWU","http://feeds.feedburner.com/~ff/Matrixsynth?a=WIKK2-Kwx-s:oDOSD79Afkk:qj6IDK7rITs"],"wordCount":"12","dataFormat":"text","duplicateGroupId":"34207128326","media":{"audio":[],"images":[],"video":[],"logo":[]},"publishingPlatform":{},"adultLanguage":"false","topics":[],"companies":[],"author":{"name":"matrix","publishingPlatform":{}},"licenses":[],"source":{"name":"MATRIXSYNTH","homeUrl":"http://www.matrixsynth.com/","location":{},"feed":{"id":"675554","name":"MATRIXSYNTH","mediaType":"Blog","publishingPlatform":"Blogger","generator":"Blogger http://www.blogger.com","description":"EVERYTHING SYNTH","tags":["Video","Featured","Auctions","Roland","Korg","MOOG","eurorack","DIY","Yamaha","Soft Synths","iOS","Audio","synth tutorials","ARP","Elektron","Buchla","Doepfer","Oberheim","Sequential Circuits","DSI","Waldorf","events","eBay","Make Noise","NAMM","Novation","New","Circuit Bending","Arturia","Updates","Akai","Clavia","sc"],"language":"English","dataFormat":"text","rank":{"autoRank":"4","autoRankOrder":"23077","inboundLinkCount":"25"},"inWhiteList":"true","autoTopics":[]}},"es_id":86992243}