{"sequenceId":"845364077532","id":"34207172483","language":"English","title":"Nutrisystem (NTRI) Expected to Post Quarterly Sales of $188.43 Million","content":"Equities analysts forecast that Nutrisystem (NASDAQ:NTRI) will report $188.43 million in sales for the current quarter, Zacks Investment Research reports. Three analysts have provided estimates for Nutrisystem’s earnings, with the highest sales estimate coming in at $189.10 million and the lowest estimate coming in at $187.70 million. Nutrisystem posted sales of $194.89 million during the […]","contentWithMarkup":"Equities analysts forecast that Nutrisystem (NASDAQ:NTRI) will report $188.43 million in sales for the current quarter, Zacks Investment Research reports. Three analysts have provided estimates for Nutrisystem’s earnings, with the highest sales estimate coming in at $189.10 million and the lowest estimate coming in at $187.70 million. Nutrisystem posted sales of $194.89 million during the […]","tags":[],"publishedDate":"2018-06-02T21:38:41Z","harvestDate":"2018-06-02T21:39:31Z","estimatedPublishedDate":"2018-06-02T21:38:41Z","url":"http://ct.moreover.com/?a=34207172483&p=1u0&v=1&x=-O723NjnRq0EjSPiKHut9Q","originalUrl":"https://www.watchlistnews.com/nutrisystem-ntri-expected-to-post-quarterly-sales-of-188-43-million/2198579.html","outboundUrls":[],"wordCount":"51","dataFormat":"text","duplicateGroupId":"34207172483","media":{"audio":[],"images":[],"video":[],"logo":[]},"publishingPlatform":{},"adultLanguage":"false","topics":[{"name":"Society news","group":"Society"}],"companies":[],"author":{"name":"Nicole Kennedy","publishingPlatform":{}},"licenses":[{"name":"CLA"}],"source":{"name":"Watch List News","homeUrl":"https://www.watchlistnews.com","category":"Press Wire","editorialRank":"4","location":{"country":"United States","countryCode":"US","region":"Americas","subregion":"Northern America"},"feed":{"id":"373455314","name":"Watch List News","mediaType":"News","tags":[],"language":"Unassigned","dataFormat":"text","rank":{"inboundLinkCount":"0"},"inWhiteList":"true","autoTopics":[],"editorialTopics":["Standard","Society","Wires"],"genre":"Press Release"}},"es_id":86992368}