{"sequenceId":"845365863636","id":"34207225326","language":"English","title":"Beacon Journal named best newspaper in Ohio","content":"You are reading the best newspaper in Ohio.    The Press Club of Cleveland named the Akron Beacon Journal the best large daily newspaper in Ohio. Judges said the Beacon Journal has a well-balanced “mix of local and national news. Great photos and overall content.”    The Plain Dealer of Cleveland took second place for best daily newspaper.    The Beacon Journal and its staff received 29 awards — 12 were for first place — at the Press Club of Cleveland’s 40th All Ohio Excellence in Journalism Awards ceremony Friday night at the House of Blues in Cleveland. There were more than 750 entries from around Ohio judged by press club members from across the country.    Edna Jakubowski received a Best in Ohio first-place award for page design. Other first-place winners were reporters Stephanie Warsmith, Rick Armon, Marla Ridenour, Clint O’Connor, Doug Livingston, Craig Webb, Nate Ulrich and Theresa Cottom. Photographers Phil Masturzo and Karen Schiely got first-place awards along with artist Rick Steinhauser.    The Beacon Journal’s Ohio.com was named the second-best newspaper website in Ohio.    Here is a list of the Beacon Journal winners:    Akron Beacon Journal — Best in Ohio: Daily newspaper, first place.    Edna Jakubowski — Best in Ohio: Page design, first place.    Bob Dyer — Best in Ohio: Essay writing, second place.    Michael Douglas — Best in Ohio: Editorial, third place.    Stephanie Warsmith, Rick Armon, breaking news, first place — Seven die in Akron house fire.    Marla Ridenour, obituary, first place — Legendary coach Ara Parseghian passes into eternity.    Phil Masturzo, studio photography, first place — Butternut squash soup.    Clint O’Connor, reviews/criticism, first place — Blade Runner 2019.    Doug Livingston, general news, first place — Call to arms.    Rick Steinhauser, illustration, first place — Bob Dylan.    Craig Webb, arts and entertainment, first place — Disc Dog league.    Nate Ulrich, sports column, first place — Failed trade bolsters Hue Jackson’s case.    Doug Livingston, Theresa Cottom, analysis, first place — Opioid epidemic: Party politics stymie resolutions.    Karen Schiely, general news photography, first place — Changed forever.    Betty Lin-Fisher, business columns, second place — Vintage tire ads preyed on concerns of motorists.    Malcolm X Abram, obituary, second place — Musician Ralph Carney.    Phil Masturzo, portrait photography, second place — Second chance.    Staff, breaking news, second place — Summa leaders to resign posts.    Amanda Garrett, Doug Livingston, Stephanie Warsmith, ongoing breaking news, second place — Police chief resigns.    Malcolm X Abram, arts and entertainment, second place — Himalayan music academy.    Clint O’Connor, personality profile, second place — Fathers, sons and “Field of Dreams.”    Mark Turner, single page design, second place — White in America.    Doug Livingston, public service, second place — Tent city.    Darrin Werbeck, Deanna Stevens, Dan Kadar, newspaper website, second place — Ohio.com .    Bob Dyer, single essay, third place — Stanley Ford case is not about police chief.    Edna Jakubowski, single page design, third place — Escape room.    Betty Lin-Fisher, consecutive days same topic, third place — Summa Health System.    Craig Webb, arts and entertainment, third place — Cleveland Orchestra has to fine tune.    Michael Douglas, single editorial, third place — Judge Adams and his “Dangerous Work.”    The post appeared first on Ohio.com .","contentWithMarkup":"You are reading the best newspaper in Ohio.    The Press Club of Cleveland named the Akron Beacon Journal the best large daily newspaper in Ohio. Judges said the Beacon Journal has a well-balanced “mix of local and national news. Great photos and overall content.”    The Plain Dealer of Cleveland took second place for best daily newspaper.    The Beacon Journal and its staff received 29 awards — 12 were for first place — at the Press Club of Cleveland’s 40th All Ohio Excellence in Journalism Awards ceremony Friday night at the House of Blues in Cleveland. There were more than 750 entries from around Ohio judged by press club members from across the country.    Edna Jakubowski received a Best in Ohio first-place award for page design. Other first-place winners were reporters Stephanie Warsmith, Rick Armon, Marla Ridenour, Clint O’Connor, Doug Livingston, Craig Webb, Nate Ulrich and Theresa Cottom. Photographers Phil Masturzo and Karen Schiely got first-place awards along with artist Rick Steinhauser.    The Beacon Journal’s Ohio.com was named the second-best newspaper website in Ohio.    Here is a list of the Beacon Journal winners:    Akron Beacon Journal — Best in Ohio: Daily newspaper, first place.    Edna Jakubowski — Best in Ohio: Page design, first place.    Bob Dyer — Best in Ohio: Essay writing, second place.    Michael Douglas — Best in Ohio: Editorial, third place.    Stephanie Warsmith, Rick Armon, breaking news, first place — Seven die in Akron house fire.    Marla Ridenour, obituary, first place — Legendary coach Ara Parseghian passes into eternity.    Phil Masturzo, studio photography, first place — Butternut squash soup.    Clint O’Connor, reviews/criticism, first place — Blade Runner 2019.    Doug Livingston, general news, first place — Call to arms.    Rick Steinhauser, illustration, first place — Bob Dylan.    Craig Webb, arts and entertainment, first place — Disc Dog league.    Nate Ulrich, sports column, first place — Failed trade bolsters Hue Jackson’s case.    Doug Livingston, Theresa Cottom, analysis, first place — Opioid epidemic: Party politics stymie resolutions.    Karen Schiely, general news photography, first place — Changed forever.    Betty Lin-Fisher, business columns, second place — Vintage tire ads preyed on concerns of motorists.    Malcolm X Abram, obituary, second place — Musician Ralph Carney.    Phil Masturzo, portrait photography, second place — Second chance.    Staff, breaking news, second place — Summa leaders to resign posts.    Amanda Garrett, Doug Livingston, Stephanie Warsmith, ongoing breaking news, second place — Police chief resigns.    Malcolm X Abram, arts and entertainment, second place — Himalayan music academy.    Clint O’Connor, personality profile, second place — Fathers, sons and “Field of Dreams.”    Mark Turner, single page design, second place — White in America.    Doug Livingston, public service, second place — Tent city.    Darrin Werbeck, Deanna Stevens, Dan Kadar, newspaper website, second place — Ohio.com .    Bob Dyer, single essay, third place — Stanley Ford case is not about police chief.    Edna Jakubowski, single page design, third place — Escape room.    Betty Lin-Fisher, consecutive days same topic, third place — Summa Health System.    Craig Webb, arts and entertainment, third place — Cleveland Orchestra has to fine tune.    Michael Douglas, single editorial, third place — Judge Adams and his “Dangerous Work.”    The post appeared first on Ohio.com .","tags":[],"publishedDate":"2018-06-02T21:43:16Z","harvestDate":"2018-06-02T21:52:05Z","estimatedPublishedDate":"2018-06-02T21:43:16Z","url":"http://ct.moreover.com/?a=34207225326&p=1u0&v=1&x=Pb7P0rUt-eHrbiqY41yI4Q","originalUrl":"https://www.ohio.com/akron/news/local/beacon-journal-named-best-newspaper-in-ohio","outboundUrls":[],"wordCount":"487","dataFormat":"text","duplicateGroupId":"34207225326","media":{"audio":[],"images":[],"video":[],"logo":[]},"publishingPlatform":{},"adultLanguage":"false","topics":[{"name":"Cleveland news","group":"US regional"}],"companies":[{"name":"Friday Night Inc","symbol":"TGIF","exchange":"CNQ","isin":"CA3583671001","titleCount":0,"contentCount":1,"primary":true},{"name":"Friday Night Inc","symbol":"TGIFF","exchange":"PINX","isin":"CA3583671001","titleCount":0,"contentCount":1,"primary":true},{"name":"Friday Night Inc","symbol":"1QF","exchange":"FRA","isin":"CA3583671001","titleCount":0,"contentCount":1,"primary":true},{"name":"Friday Night Inc","symbol":"1QF","exchange":"MUN","isin":"CA3583671001","titleCount":0,"contentCount":1,"primary":true},{"name":"Friday Night Inc","symbol":"1QF","exchange":"BER","isin":"CA3583671001","titleCount":0,"contentCount":1,"primary":true}],"author":{"name":"Beacon Journal/Ohio.com","publishingPlatform":{}},"licenses":[{"name":"Publicly Available"}],"source":{"name":"Akron Beacon Journal","homeUrl":"http://www.ohio.com","category":"Local","editorialRank":"4","location":{"country":"United States","countryCode":"US","region":"Americas","subregion":"Northern America","state":"Ohio","county":"Summit","zipArea":"Akron","zipCode":"44308"},"feed":{"id":"169658102","name":"Akron Beacon Journal","mediaType":"News","tags":[],"language":"Unassigned","dataFormat":"text","rank":{"inboundLinkCount":"3544"},"inWhiteList":"true","autoTopics":[],"editorialTopics":["Geographic","Local","News","Standard"],"genre":"General"}},"es_id":86993865}