{"sequenceId":"845366193121","id":"34207234897","language":"English","title":"Applications invited to change schools","content":"STUDENTS wishing to switch schools have been urged to visit the Education Ministry’s customer services building in Isa Town tomorrow. They should carry relevant documents, and applications will be accepted until Thursday, from 9am to 1pm .  You Might Like","contentWithMarkup":"STUDENTS wishing to switch schools have been urged to visit the Education Ministry’s customer services building in Isa Town tomorrow. They should carry relevant documents, and applications will be accepted until Thursday, from 9am to 1pm .  You Might Like","tags":[],"harvestDate":"2018-06-02T21:54:32Z","estimatedPublishedDate":"2018-06-02T21:54:32Z","url":"http://ct.moreover.com/?a=34207234897&p=1u0&v=1&x=LTmIYwynVvndnwq62_XMPQ","originalUrl":"http://www.gdnonline.com/Details/365557/Applications-invited-to-change-schools","outboundUrls":[],"wordCount":"39","dataFormat":"text","duplicateGroupId":"34207234897","media":{"audio":[],"images":[{"url":"http://www.gdnonline.com/gdnimages/20180602%5C20180602235402re.JPG"}],"video":[],"logo":[]},"publishingPlatform":{},"adultLanguage":"false","topics":[{"name":"Society news","group":"Society"},{"name":"Education news","group":"Society"}],"companies":[],"author":{"publishingPlatform":{}},"licenses":[{"name":"CLA"}],"source":{"name":"Gulf Daily News","homeUrl":"http://www.gdnonline.com","publisher":"Gulf Daily News","category":"National","editorialRank":"1","location":{"country":"Bahrain","countryCode":"BH","region":"Asia","subregion":"Western Asia"},"feed":{"id":"169714865","name":"Gulf Daily News","mediaType":"News","tags":[],"language":"Unassigned","dataFormat":"text","rank":{"inboundLinkCount":"28"},"inWhiteList":"true","autoTopics":[],"editorialTopics":["Geographic","National","Standard","News"],"genre":"General"}},"es_id":86994151}