{"sequenceId":"845364091323","id":"34207173111","language":"English","title":"Body found at Plainville High School; police investigating","content":"PLAINVILLE --  Police are investigating a body that was found at the Plainville High School Saturday.  Police said they responded to the scene around 1:15 p.m. and have since cleared the scene.  There is no word where the body was found on school grounds. No identity or the cause of the death has been released at this time.  This is a developing story. ","contentWithMarkup":"<a href=\"http://fox61.com/tag/plainville\">PLAINVILLE</a> --  Police are investigating a body that was found at the Plainville High School Saturday.\n\nPolice said they responded to the scene around 1:15 p.m. and have since cleared the scene.\n\nThere is no word where the body was found on school grounds. No identity or the cause of the death has been released at this time.\n\n<em>This is a developing story. </em>","tags":["News","plainville"],"publishedDate":"2018-06-02T21:39:37Z","harvestDate":"2018-06-02T21:39:43Z","estimatedPublishedDate":"2018-06-02T21:39:37Z","url":"http://ct.moreover.com/?a=34207173111&p=1u0&v=1&x=KkI5r4mXhLj1FMElyulvWA","originalUrl":"http://fox61.com/2018/06/02/body-found-at-plainville-high-school-police-investigating/","outboundUrls":[],"wordCount":"61","dataFormat":"text","duplicateGroupId":"34207173111","media":{"audio":[],"images":[],"video":[],"logo":[]},"publishingPlatform":{"itemId":"447591"},"adultLanguage":"false","topics":[],"companies":[],"author":{"name":"Rick Lessard","publishingPlatform":{"userId":"114371335"}},"licenses":[],"source":{"name":"FOX 61","homeUrl":"http://fox61.com","location":{"country":"United States","countryCode":"US","region":"Americas","subregion":"Northern America"},"feed":{"id":"561505590","name":"FOX 61","mediaType":"Blog","publishingPlatform":"WordPress","idFromPublisher":"49123914","generator":"http://wordpress.com/","description":"Connecticut breaking news, weather, traffic, sports and social media","tags":[],"language":"English","dataFormat":"text","rank":{"autoRank":"1","autoRankOrder":"1087","inboundLinkCount":"2230"},"inWhiteList":"true","autoTopics":[]}},"es_id":86992392}