{"sequenceId":"845366343628","id":"34207239718","language":"English","title":"How hit song 'Abraham, Martin and John' helped console a grieving nation","content":"One listen was enough for an unimpressed Dion DiMucci to dismiss the song sent his way in the summer of 1968.    First, there were the lyrics: Invoking the still open wounds of the April assassination of Martin Luther King Jr. and the June murder of Robert Kennedy.    And the arrangement: The demo version...","contentWithMarkup":"One listen was enough for an unimpressed Dion DiMucci to dismiss the song sent his way in the summer of 1968.    First, there were the lyrics: Invoking the still open wounds of the April assassination of Martin Luther King Jr. and the June murder of Robert Kennedy.    And the arrangement: The demo version...","tags":[],"publishedDate":"2018-06-02T21:45:00Z","harvestDate":"2018-06-02T21:55:55Z","estimatedPublishedDate":"2018-06-02T21:45:00Z","url":"http://ct.moreover.com/?a=34207239718&p=1u0&v=1&x=bJACcBrB_DVsyIcGuo08rg","originalUrl":"http://www.nydailynews.com/news/ny-news-rfk-assassination-dion-dimucci-20180602-story.html","outboundUrls":[],"wordCount":"52","dataFormat":"text","duplicateGroupId":"34207239718","media":{"audio":[],"images":[{"url":"http://www.trbimg.com/img-5b12fe4a/turbine/ny-1527971396-nebxjr6nhh-snap-image"}],"video":[],"logo":[]},"publishingPlatform":{},"adultLanguage":"false","topics":[],"companies":[],"author":{"name":"Larry McShane","publishingPlatform":{}},"licenses":[{"name":"Publicly Available"}],"source":{"name":"New York Daily News","homeUrl":"http://nydailynews.com","category":"Local","editorialRank":"4","location":{"country":"United States","countryCode":"US","region":"Americas","subregion":"Northern America","state":"New York","county":"New York","zipArea":"New York","zipCode":"10004"},"feed":{"id":"169657360","name":"New York Daily News","mediaType":"News","tags":[],"language":"Unassigned","dataFormat":"text","rank":{"inboundLinkCount":"9649"},"inWhiteList":"true","autoTopics":[],"editorialTopics":["Geographic","Local","Standard","News"],"genre":"General"}},"es_id":86994280}